cctv_detector/__init__.py
cctv_detector/detector.py
cctv_detector/visualizer.py
cctv_detector/webapp.py
cctv_detector-0.1.1.dist-info/LICENSE
cctv_detector-0.1.1.dist-info/METADATA
cctv_detector-0.1.1.dist-info/WHEEL
cctv_detector-0.1.1.dist-info/top_level.txt
cctv_detector-0.1.1.dist-info/RECORD
